genericlib/__init__.py
genericlib/collection.py
genericlib/config.py
genericlib/constant.py
genericlib/constnum.py
genericlib/constpattern.py
genericlib/conststruct.py
genericlib/constsymbol.py
genericlib/datatype.py
genericlib/decorators.py
genericlib/exceptions.py
genericlib/file.py
genericlib/misc.py
genericlib/number.py
genericlib/platform.py
genericlib/robotframeworklib.py
genericlib/search.py
genericlib/shell.py
genericlib/text.py
genericlib/utils.py
genericlib-0.6.2a1.dist-info/licenses/LICENSE
genericlib-0.6.2a1.dist-info/METADATA
genericlib-0.6.2a1.dist-info/WHEEL
genericlib-0.6.2a1.dist-info/top_level.txt
genericlib-0.6.2a1.dist-info/RECORD
